logprog_lab1/__init__.py
logprog_lab1/main.py
logprog_lab1-1.2.2.dist-info/LICENSE.txt
logprog_lab1-1.2.2.dist-info/METADATA
logprog_lab1-1.2.2.dist-info/WHEEL
logprog_lab1-1.2.2.dist-info/top_level.txt
logprog_lab1-1.2.2.dist-info/RECORD
